{
  "tenantId": "pb.amritsar",
  "moduleName": "BillingService",
  "BusinessService": [
    {
      "businessService": "PropertyTax",
      "code": "PT",
      "collectionModesNotAllowed": [
        "DD","OFFLINE_NEFT","OFFLINE_RTGS","POSTAL_ORDER"
      ],
      "partPaymentAllowed": true,
      "minAmountPayable":100,
      "isAdvanceAllowed": false,
      "demandUpdateTime": 86400000,
      "isVoucherCreationEnabled": true,
      "billGineiURL" : "egov-searcher/bill-genie/billswithaddranduser/_get"
    },
    {
      "businessService": "WaterCharges",
      "code": "WC",
      "collectionModesNotAllowed": [
        "DD","OFFLINE_NEFT","OFFLINE_RTGS","POSTAL_ORDER"
      ],
      "partPaymentAllowed": false,
      "isAdvanceAllowed": true,
      "demandUpdateTime": 86400000,
      "isVoucherCreationEnabled": false
    },
    {
      "businessService": "TradeLicense",
      "code": "TL",
      "collectionModesNotAllowed": [
        "DD","OFFLINE_NEFT","OFFLINE_RTGS","POSTAL_ORDER"
      ],
      "partPaymentAllowed": false,
      "isAdvanceAllowed": false,
      "demandUpdateTime": 604800000,
      "isVoucherCreationEnabled": true
    },
    {
      "businessService": "WaterCharges.Metered",
      "code": "WaterCharges.Metered",
      "collectionModesNotAllowed": [
        "DD"
      ],
      "partPaymentAllowed": false,
      "isAdvanceAllowed": true,
      "demandUpdateTime": 86400000,
      "isVoucherCreationEnabled": false,
      "type": "Adhoc"
    },
    {
      "businessService": "WaterCharges.NonMetered",
      "code": "WaterCharges.NonMetered",
      "collectionModesNotAllowed": [
        "DD"
      ],
      "partPaymentAllowed": false,
      "isAdvanceAllowed": true,
      "demandUpdateTime": 86400000,
      "isVoucherCreationEnabled": false,
      "type": "Adhoc"
    },
    {
      "businessService": "FIRENOC",
      "code": "FIRENOC",
      "collectionModesNotAllowed": [
        "DD","OFFLINE_NEFT","OFFLINE_RTGS","POSTAL_ORDER"
      ],
      "partPaymentAllowed": false,
      "isAdvanceAllowed": false,
      "isVoucherCreationEnabled": true,
      "isActive": true,
      "type": "Adhoc"
    },
    {
      "businessService": "Taxes.No Dues Certificate",
      "code": "TX.No_Dues_Certificate",
      "collectionModesNotAllowed": [
        "DD"
      ],
      "partPaymentAllowed": false,
      "isAdvanceAllowed": false,
      "isVoucherCreationEnabled": true,
      "type": "Adhoc"
    },
    {
      "businessService": "Advertisement Tax.Hoardings",
      "code": "ADVT.Hoardings",
      "collectionModesNotAllowed": [
        "DD"
      ],
      "partPaymentAllowed": false,
      "isAdvanceAllowed": true,
      "demandUpdateTime": 86400000,
      "isVoucherCreationEnabled": false,
      "type": "Adhoc"
    },
    {
      "businessService": "Advertisement Tax.Unipolls",
      "code": "ADVT.Unipolls",
      "collectionModesNotAllowed": [
        "DD"
      ],
      "partPaymentAllowed": false,
      "isAdvanceAllowed": false,
      "isVoucherCreationEnabled": true,
      "isActive": true,
      "type": "Adhoc"
    },
    {
      "businessService": "Rents.Municipal Shops Rent",
      "code": "RT.Municipal_Shops_Rent",
      "collectionModesNotAllowed": [
        "DD"
      ],
      "partPaymentAllowed": false,
      "isAdvanceAllowed": false,
      "isVoucherCreationEnabled": true,
      "isActive": true,
      "type": "Adhoc"
    },
    {
      "businessService": "Rents.Land Rent",
      "code": "RT.Land_Rent",
      "collectionModesNotAllowed": [
        "DD"
      ],
      "partPaymentAllowed": false,
      "isAdvanceAllowed": false,
      "isVoucherCreationEnabled": true,
      "isActive": true,
      "type": "Adhoc"
    },
    {
      "businessService": "Rents.Tower Rent",
      "code": "RT.Tower_Rent",
      "collectionModesNotAllowed": [
        "DD"
      ],
      "partPaymentAllowed": false,
      "isAdvanceAllowed": false,
      "isVoucherCreationEnabled": true,
      "isActive": true,
      "type": "Adhoc"
    },
    {
      "businessService": "Rents.Parking Fee",
      "code": "RT.Parking_Fee",
      "collectionModesNotAllowed": [
        "DD"
      ],
      "partPaymentAllowed": false,
      "isAdvanceAllowed": false,
      "isVoucherCreationEnabled": true,
      "isActive": true,
      "type": "Adhoc"
    },
    {
      "businessService": "Rents.Jamin Theka",
      "code": "RT.Jamin_Theka",
      "collectionModesNotAllowed": [
        "DD"
      ],
      "partPaymentAllowed": false,
      "isAdvanceAllowed": false,
      "isVoucherCreationEnabled": true,
      "isActive": true,
      "type": "Adhoc"
    },
    {
      "businessService": "ADMIN Fees.Election rally fees",
      "code": "ADMN.Election_rally_fees",
      "collectionModesNotAllowed": [
        "DD"
      ],
      "partPaymentAllowed": false,
      "isAdvanceAllowed": false,
      "isVoucherCreationEnabled": true,
      "isActive": true,
      "type": "Adhoc"
    },
    {
      "businessService": "ADMIN Fees.Parking during election",
      "code": "ADMN.Parking_during_election",
      "collectionModesNotAllowed": [
        "DD"
      ],
      "partPaymentAllowed": false,
      "isAdvanceAllowed": false,
      "isVoucherCreationEnabled": true,
      "isActive": true,
      "type": "Adhoc"
    },
    {
      "businessService": "ADMIN Fees.Road show",
      "code": "ADMN.Road_show",
      "collectionModesNotAllowed": [
        "DD"
      ],
      "partPaymentAllowed": false,
      "isAdvanceAllowed": false,
      "isVoucherCreationEnabled": true,
      "isActive": true,
      "type": "Adhoc"
    },
    {
      "businessService": "Finance Fees.Advance Provident Fund",
      "code": "FN.Advance_Provident_Fund",
      "collectionModesNotAllowed": [
        "DD"
      ],
      "partPaymentAllowed": false,
      "isAdvanceAllowed": false,
      "isVoucherCreationEnabled": true,
      "isActive": true,
      "type": "Adhoc"
    },
    {
      "businessService": "Stationary.Stationary (Not Income)",
      "code": "ST.Stationary_Not_Income",
      "collectionModesNotAllowed": [
        "DD"
      ],
      "partPaymentAllowed": false,
      "isAdvanceAllowed": false,
      "isVoucherCreationEnabled": true,
      "isActive": true,
      "type": "Adhoc"
    },
    {
      "businessService": "Stationary.Expenditure santitation (Not Income)",
      "code": "ST.Expenditure_santitation_Not_Income",
      "collectionModesNotAllowed": [
        "DD"
      ],
      "partPaymentAllowed": false,
      "isAdvanceAllowed": false,
      "isVoucherCreationEnabled": true,
      "isActive": true,
      "type": "Adhoc"
    },
    {
      "businessService": "Challans.Santitation dumping garbage",
      "code": "CH.Santitation_dumping_garbage",
      "collectionModesNotAllowed": [
        "DD"
      ],
      "partPaymentAllowed": false,
      "isAdvanceAllowed": false,
      "isVoucherCreationEnabled": true,
      "isActive": true,
      "type": "Adhoc"
    },
    {
      "businessService": "Fee Town Planning.Telecom tower fees",
      "code": "FTP.Telecom_tower_fees",
      "collectionModesNotAllowed": [
        "DD"
      ],
      "partPaymentAllowed": false,
      "isAdvanceAllowed": false,
      "isVoucherCreationEnabled": true,
      "isActive": true,
      "type": "Adhoc"
    },
    {
      "businessService": "Taxes.Electricity Chungi",
      "code": "TX.Electricity_Chungi",
      "collectionModesNotAllowed": [
        "DD"
      ],
      "partPaymentAllowed": false,
      "isAdvanceAllowed": false,
      "isVoucherCreationEnabled": true,
      "isActive": true,
      "type": "Adhoc"
    },
    {
      "businessService": "Fee Town Planning.Draftsmen fees",
      "code": "FTP.Draftsmen_fees",
      "collectionModesNotAllowed": [
        "DD"
      ],
      "partPaymentAllowed": false,
      "isAdvanceAllowed": false,
      "isVoucherCreationEnabled": true,
      "isActive": true,
      "type": "Adhoc"
    },
    {
      "businessService": "Fee Town Planning.Compremasing fees",
      "code": "FTP.Compremasing_fees",
      "collectionModesNotAllowed": [
        "DD"
      ],
      "partPaymentAllowed": false,
      "isAdvanceAllowed": false,
      "isVoucherCreationEnabled": true,
      "isActive": true,
      "type": "Adhoc"
    },
    {
      "businessService": "Fee Town Planning.Building planner renew",
      "code": "FTP.Building_planner_renew",
      "collectionModesNotAllowed": [
        "DD"
      ],
      "partPaymentAllowed": false,
      "isAdvanceAllowed": false,
      "isVoucherCreationEnabled": true,
      "isActive": true,
      "type": "Adhoc"
    },
    {
      "businessService": "Naksha/Building Manual Fees.Naksha samjota fees",
      "code": "NKS.Naksha_samjota_fees",
      "collectionModesNotAllowed": [
        "DD"
      ],
      "partPaymentAllowed": false,
      "isAdvanceAllowed": false,
      "isVoucherCreationEnabled": true,
      "isActive": true,
      "type": "Adhoc"
    },
    {
      "businessService": "Naksha/Building Manual Fees.Naksha changes ",
      "code": "NKS.Naksha_changes",
      "collectionModesNotAllowed": [
        "DD"
      ],
      "partPaymentAllowed": false,
      "isAdvanceAllowed": false,
      "isVoucherCreationEnabled": true,
      "isActive": true,
      "type": "Adhoc"
    },
    {
      "businessService": "Fee Town Planning.License fees building branch",
      "code": "FTP.License_fees_building_branch",
      "collectionModesNotAllowed": [
        "DD"
      ],
      "partPaymentAllowed": false,
      "isAdvanceAllowed": false,
      "isVoucherCreationEnabled": true,
      "isActive": true,
      "type": "Adhoc"
    },
    {
      "businessService": "O&M Fee.Water connection/disconnection fees",
      "code": "OM.Water_connection/disconnection_fees",
      "collectionModesNotAllowed": [
        "DD"
      ],
      "partPaymentAllowed": false,
      "isAdvanceAllowed": false,
      "isVoucherCreationEnabled": true,
      "isActive": true,
      "type": "Adhoc"
    },
    {
      "businessService": "Naksha/Building Manual Fees.Naksha renew fees",
      "code": "NKS.Naksha_renew_fees",
      "collectionModesNotAllowed": [
        "DD"
      ],
      "partPaymentAllowed": false,
      "isAdvanceAllowed": false,
      "isVoucherCreationEnabled": true,
      "isActive": true,
      "type": "Adhoc"
    },
    {
      "businessService": "Naksha/Building Manual Fees.NOC/Completion of building approval",
      "code": "NKS.NOC/Completion_of_building_approval",
      "collectionModesNotAllowed": [
        "DD"
      ],
      "partPaymentAllowed": false,
      "isAdvanceAllowed": false,
      "isVoucherCreationEnabled": true,
      "isActive": true,
      "type": "Adhoc"
    },
    {
      "businessService": "Naksha/Building Manual Fees.Alteration additional charge",
      "code": "NKS.Alteration_additional_charge",
      "collectionModesNotAllowed": [
        "DD"
      ],
      "partPaymentAllowed": false,
      "isAdvanceAllowed": false,
      "isVoucherCreationEnabled": true,
      "isActive": true,
      "type": "Adhoc"
    },
    {
      "businessService": "Naksha/Building Manual Fees.2 year time limit of Renewal Building Naksha",
      "code": "NKS.2_year_time_limit_of_Renewal_Building_Naksha",
      "collectionModesNotAllowed": [
        "DD"
      ],
      "partPaymentAllowed": false,
      "isAdvanceAllowed": false,
      "isVoucherCreationEnabled": true,
      "isActive": true,
      "type": "Adhoc"
    },
    {
      "businessService": "Fee Town Planning.Leave encashment and gratuty",
      "code": "FTP.Leave_encashment_and_gratuty",
      "collectionModesNotAllowed": [
        "DD"
      ],
      "partPaymentAllowed": false,
      "isAdvanceAllowed": false,
      "isVoucherCreationEnabled": true,
      "isActive": true,
      "type": "Adhoc"
    },
    {
      "businessService": "Challans.Plastic Challan",
      "code": "CH.Plastic_Challan",
      "collectionModesNotAllowed": [
        "DD"
      ],
      "partPaymentAllowed": false,
      "isAdvanceAllowed": false,
      "isVoucherCreationEnabled": true,
      "isActive": true,
      "type": "Adhoc"
    },
    {
      "businessService": "Challans.Rehri Challan",
      "code": "CH.Rehri_Challan",
      "collectionModesNotAllowed": [
        "DD"
      ],
      "partPaymentAllowed": false,
      "isAdvanceAllowed": false,
      "isVoucherCreationEnabled": true,
      "isActive": true,
      "type": "Adhoc"
    },
    {
      "businessService": "Challans.Challan for Misuse of Water",
      "code": "CH.Challan_for_Misuse_of_Water",
      "collectionModesNotAllowed": [
        "DD"
      ],
      "partPaymentAllowed": false,
      "isAdvanceAllowed": false,
      "isVoucherCreationEnabled": true,
      "isActive": true,
      "type": "Adhoc"
    },
    {
      "businessService": "Challans.Dengue Challan",
      "code": "CH.Dengue_Challan",
      "collectionModesNotAllowed": [
        "DD"
      ],
      "partPaymentAllowed": false,
      "isAdvanceAllowed": false,
      "isVoucherCreationEnabled": true,
      "isActive": true,
      "type": "Adhoc"
    },
    {
      "businessService": "Challans.Littering Challan",
      "code": "CH.Littering_Challan",
      "collectionModesNotAllowed": [
        "DD"
      ],
      "partPaymentAllowed": false,
      "isAdvanceAllowed": false,
      "isVoucherCreationEnabled": true,
      "isActive": true,
      "type": "Adhoc"
    },
    {
      "businessService": "Sanitation.Licence Pure food",
      "code": "SNT.Licence_Pure_food",
      "collectionModesNotAllowed": [
        "DD"
      ],
      "partPaymentAllowed": false,
      "isAdvanceAllowed": false,
      "isVoucherCreationEnabled": true,
      "isActive": true,
      "type": "Adhoc"
    },
    {
      "businessService": "OTHER.Misc Challans",
      "code": "OTHER.Misc_Challans",
      "collectionModesNotAllowed": [
        "DD"
      ],
      "partPaymentAllowed": false,
      "isAdvanceAllowed": false,
      "isVoucherCreationEnabled": true,
      "isActive": true,
      "type": "Adhoc"
    },
    {
      "businessService": "Naksha/Building Manual Fees.Regularisation of Buildings",
      "code": "NKS.Regularisation_of_Buildings",
      "collectionModesNotAllowed": [
        "DD"
      ],
      "partPaymentAllowed": false,
      "isAdvanceAllowed": false,
      "isVoucherCreationEnabled": true,
      "isActive": true,
      "type": "Adhoc"
    },
    {
      "businessService": "Work Fee.Contractor Enlistment",
      "code": "WF.Contractor_Enlistment",
      "collectionModesNotAllowed": [
        "DD"
      ],
      "partPaymentAllowed": false,
      "isAdvanceAllowed": false,
      "isVoucherCreationEnabled": true,
      "isActive": true,
      "type": "Adhoc"
    },
    {
      "businessService": "Work Fee.Tender Form Fee",
      "code": "WF.Tender Form Fee",
      "collectionModesNotAllowed": [
        "DD"
      ],
      "partPaymentAllowed": false,
      "isAdvanceAllowed": false,
      "isVoucherCreationEnabled": true,
      "isActive": true,
      "type": "Adhoc"
    },
    {
      "businessService": "Tehbazaari Fee.Advertisement fee",
      "code": "TB.Advertisement_fee",
      "collectionModesNotAllowed": [
        "DD"
      ],
      "partPaymentAllowed": false,
      "isAdvanceAllowed": false,
      "isVoucherCreationEnabled": true,
      "isActive": true,
      "type": "Adhoc"
    },
    {
      "businessService": "Tehbazaari Fee.Tehbazaari",
      "code": "TB.Tehbazaari",
      "collectionModesNotAllowed": [
        "DD"
      ],
      "partPaymentAllowed": false,
      "isAdvanceAllowed": false,
      "isVoucherCreationEnabled": true,
      "isActive": true,
      "type": "Adhoc"
    },
    {
      "businessService": "Finance Fees.PF transfer (Accounts)",
      "code": "FN.PF_transfer_(Accounts)",
      "collectionModesNotAllowed": [
        "DD"
      ],
      "partPaymentAllowed": false,
      "isAdvanceAllowed": false,
      "isVoucherCreationEnabled": true,
      "isActive": true,
      "type": "Adhoc"
    },
    {
      "businessService": "Taxes.TS1 copy register for old survey",
      "code": "TX.TS1_copy_register_for_old_survey",
      "collectionModesNotAllowed": [
        "DD"
      ],
      "partPaymentAllowed": false,
      "isAdvanceAllowed": false,
      "isVoucherCreationEnabled": true,
      "isActive": true,
      "type": "Adhoc"
    },
    {
      "businessService": "Taxes.Transfer Property Fees",
      "code": "TX.Transfer_Property_Fees",
      "collectionModesNotAllowed": [
        "DD"
      ],
      "partPaymentAllowed": false,
      "isAdvanceAllowed": false,
      "isVoucherCreationEnabled": true,
      "isActive": true,
      "type": "Adhoc"
    },
    {
      "businessService": "ADMIN Fees.RTI",
      "code": "ADMN.RTI",
      "collectionModesNotAllowed": [
        "DD"
      ],
      "partPaymentAllowed": false,
      "isAdvanceAllowed": false,
      "isVoucherCreationEnabled": true,
      "isActive": true,
      "type": "Adhoc"
    },
    {
      "businessService": "ADMIN Fees.No Dues Certificate",
      "code": "ADMN.No_Dues_Certificate",
      "collectionModesNotAllowed": [
        "DD"
      ],
      "partPaymentAllowed": false,
      "isAdvanceAllowed": false,
      "isVoucherCreationEnabled": true,
      "isActive": true,
      "type": "Adhoc"
    },
    {
      "businessService": "Fee Town Planning.Architect license fee",
      "code": "FTP.Architect_license_fee",
      "collectionModesNotAllowed": [
        "DD"
      ],
      "partPaymentAllowed": false,
      "isAdvanceAllowed": false,
      "isVoucherCreationEnabled": true,
      "isActive": true,
      "type": "Adhoc"
    },
    {
      "businessService": "Tehbazaari Fee.Challan Under section 156",
      "code": "Tehbazaari Fee.Challan_Under_section_156",
      "collectionModesNotAllowed": [
        "DD"
      ],
      "partPaymentAllowed": false,
      "isAdvanceAllowed": false,
      "isVoucherCreationEnabled": true,
      "isActive": true,
      "type": "Adhoc"
    },
    {
      "businessService": "Finance Fees.Recovery employee/contractor",
      "code": "FN.Recovery_employee/contractor",
      "collectionModesNotAllowed": [
        "DD"
      ],
      "partPaymentAllowed": false,
      "isAdvanceAllowed": false,
      "isVoucherCreationEnabled": true,
      "isActive": true,
      "type": "Adhoc"
    },
    {
      "businessService": "Finance Fees.Grants cheque",
      "code": "FN.Grants_cheque",
      "collectionModesNotAllowed": [
        "DD"
      ],
      "partPaymentAllowed": false,
      "isAdvanceAllowed": false,
      "isVoucherCreationEnabled": true,
      "isActive": true,
      "type": "Adhoc"
    },
    {
      "businessService": "OTHER.No due certificate electricity",
      "code": "OTHER.No_due_certificate_electricity",
      "collectionModesNotAllowed": [
        "DD"
      ],
      "partPaymentAllowed": false,
      "isAdvanceAllowed": false,
      "isVoucherCreationEnabled": true,
      "isActive": true,
      "type": "Adhoc"
    },
    {
      "businessService": "OTHER.registery and bank loan",
      "code": "OTHER.registery_and_bank_loan",
      "collectionModesNotAllowed": [
        "DD"
      ],
      "partPaymentAllowed": false,
      "isAdvanceAllowed": false,
      "isVoucherCreationEnabled": true,
      "isActive": true,
      "type": "Adhoc"
    },
    {
      "businessService": "SBM garbage plastic polythene challan",
      "code": "CH.SBM_garbage_plastic_polythene_challan",
      "collectionModesNotAllowed": [
        "DD"
      ],
      "partPaymentAllowed": false,
      "isAdvanceAllowed": false,
      "isVoucherCreationEnabled": true,
      "isActive": true,
      "type": "Adhoc"
    },
    {
      "businessService": "Sanitation.Dead animals contract",
      "code": "SNT.Dead_animals_contract",
      "collectionModesNotAllowed": [
        "DD"
      ],
      "partPaymentAllowed": false,
      "isAdvanceAllowed": false,
      "isVoucherCreationEnabled": true,
      "isActive": true,
      "type": "Adhoc"
    },
    {
      "businessService": "Finance Fees.GPF",
      "code": "FN.GPF",
      "collectionModesNotAllowed": [
        "DD"
      ],
      "partPaymentAllowed": false,
      "isAdvanceAllowed": false,
      "isVoucherCreationEnabled": true,
      "isActive": true,
      "type": "Adhoc"
    },
    {
      "businessService": "Finance Fees.CPF received check",
      "code": "FN.CPF_received_check",
      "collectionModesNotAllowed": [
        "DD"
      ],
      "partPaymentAllowed": false,
      "isAdvanceAllowed": false,
      "isVoucherCreationEnabled": true,
      "isActive": true,
      "type": "Adhoc"
    },
    {
      "businessService": "Rents.Tower Installation",
      "code": "RT.Tower_Installation",
      "collectionModesNotAllowed": [
        "DD"
      ],
      "partPaymentAllowed": false,
      "isAdvanceAllowed": false,
      "isVoucherCreationEnabled": true,
      "isActive": true,
      "type": "Adhoc"
    },
    {
      "businessService": "Rents.Tower Annual Rent",
      "code": "RT.Tower_Annual_Rent",
      "collectionModesNotAllowed": [
        "DD"
      ],
      "partPaymentAllowed": false,
      "isAdvanceAllowed": false,
      "isVoucherCreationEnabled": true,
      "isActive": true,
      "type": "Adhoc"
    },
    {
      "businessService": "Cess.Cow Cess",
      "code": "CSS.cow_cess",
      "collectionModesNotAllowed": [
        "DD"
      ],
      "partPaymentAllowed": false,
      "isAdvanceAllowed": false,
      "isVoucherCreationEnabled": true,
      "isActive": true,
      "type": "Adhoc"
    },
    {
      "businessService": "Challans.Cattle Challan",
      "code": "CH.Cattle_Challan",
      "collectionModesNotAllowed": [
        "DD"
      ],
      "partPaymentAllowed": false,
      "isAdvanceAllowed": false,
      "isVoucherCreationEnabled": true,
      "isActive": true,
      "type": "Adhoc"
    },
    {
      "businessService": "Tehbazaari Fee.Rehri Challan",
      "code": "TB.Rehri_Challan",
      "collectionModesNotAllowed": [
        "DD"
      ],
      "partPaymentAllowed": false,
      "isAdvanceAllowed": false,
      "isVoucherCreationEnabled": true,
      "isActive": true,
      "type": "Adhoc"
    },
    {
      "businessService": "License Fee.Manual Rikshaw",
      "code": "LCF.Manual_Rikshaw",
      "collectionModesNotAllowed": [
        "DD"
      ],
      "partPaymentAllowed": false,
      "isAdvanceAllowed": false,
      "isVoucherCreationEnabled": true,
      "isActive": true,
      "type": "Adhoc"
    },
    {
      "businessService": "Challans.Dairy Animals Challan",
      "code": "CH.Dairy_Animals_Challan",
      "collectionModesNotAllowed": [
        "DD"
      ],
      "partPaymentAllowed": false,
      "isAdvanceAllowed": false,
      "isVoucherCreationEnabled": true,
      "isActive": true,
      "type": "Adhoc"
    },
    {
      "businessService": "Challans.Bidi & Cigrette Challan",
      "code": "CH.Bidi_&_Cigrette_Challan",
      "collectionModesNotAllowed": [
        "DD"
      ],
      "partPaymentAllowed": false,
      "isAdvanceAllowed": false,
      "isVoucherCreationEnabled": true,
      "isActive": true,
      "type": "Adhoc"
    },
    {
      "businessService": "Rents.Community Centre Booking Fee",
      "code": "RT.Community_Centre_Booking_Fee",
      "collectionModesNotAllowed": [
        "DD"
      ],
      "partPaymentAllowed": false,
      "isAdvanceAllowed": false,
      "isVoucherCreationEnabled": true,
      "isActive": true,
      "type": "Adhoc"
    },
    {
      "businessService": "Rents.Commercial Use of Municipal Land",
      "code": "RT.Commercial_Use_of_Municipal_Land",
      "collectionModesNotAllowed": [
        "DD"
      ],
      "partPaymentAllowed": false,
      "isAdvanceAllowed": false,
      "isVoucherCreationEnabled": true,
      "isActive": true,
      "type": "Adhoc"
    },
    {
      "businessService": "Rents.Street Vendor",
      "code": "RT.Street_Vendor",
      "collectionModesNotAllowed": [
        "DD"
      ],
      "partPaymentAllowed": false,
      "isAdvanceAllowed": false,
      "isVoucherCreationEnabled": true,
      "isActive": true,
      "type": "Adhoc"
    },
    {
      "businessService": "Fee Town Planning.Construction Waste",
      "code": "FTP.Construction_Waste",
      "collectionModesNotAllowed": [
        "DD"
      ],
      "partPaymentAllowed": false,
      "isAdvanceAllowed": false,
      "isVoucherCreationEnabled": true,
      "isActive": true,
      "type": "Adhoc"
    },
    {
      "businessService": "Fee Town Planning.Demolition Waste",
      "code": "FTP.Demolition_Waste",
      "collectionModesNotAllowed": [
        "DD"
      ],
      "partPaymentAllowed": false,
      "isAdvanceAllowed": false,
      "isVoucherCreationEnabled": true,
      "isActive": true,
      "type": "Adhoc"
    },
    {
      "businessService": "Sanitation.SNT Clean/Safai Sanitation",
      "code": "SNT.clean_safai_sanitation",
      "collectionModesNotAllowed": [
        "DD"
      ],
      "partPaymentAllowed": false,
      "isAdvanceAllowed": false,
      "isVoucherCreationEnabled": true,
      "isActive": true,
      "type": "Adhoc"
    },
    {
      "businessService": "O&M Fee.Plumber License Fee",
      "code": "OM.Plumber_License_Fee",
      "collectionModesNotAllowed": [
        "DD"
      ],
      "partPaymentAllowed": false,
      "isAdvanceAllowed": false,
      "isVoucherCreationEnabled": true,
      "isActive": true,
      "type": "Adhoc"
    },
    {
      "businessService": "Advertisement Tax.Light Wala Board",
      "code": "ADVT.Light_Wala_Board",
      "collectionModesNotAllowed": [
        "DD"
      ],
      "partPaymentAllowed": false,
      "isAdvanceAllowed": false,
      "isVoucherCreationEnabled": true,
      "isActive": true,
      "type": "Adhoc"
    },
    {
      "businessService": "Advertisement Tax.Wall Paint Advertisement",
      "code": "ADVT.Wall_Paint_Advertisement",
      "collectionModesNotAllowed": [
        "DD"
      ],
      "partPaymentAllowed": false,
      "isAdvanceAllowed": false,
      "isVoucherCreationEnabled": true,
      "isActive": true,
      "type": "Adhoc"
    },
    {
      "businessService": "Advertisement Tax.Gas Balloon Advertisement",
      "code": "ADVT.Gas_Balloon_Advertisement",
      "collectionModesNotAllowed": [
        "DD"
      ],
      "partPaymentAllowed": false,
      "isAdvanceAllowed": false,
      "isVoucherCreationEnabled": true,
      "isActive": true
    },
    {
      "businessService": "Revenue Grants",
      "code": "REV_GRANTS",
      "collectionModesNotAllowed": [
        "DD"
      ],
      "partPaymentAllowed": false,
      "isAdvanceAllowed": false,
      "isVoucherCreationEnabled": true,
      "isActive": true,
      "type": "Finance"
    },
    {
      "businessService": "Disposal of Fixed Asset.Land",
      "code": "DISP_FIXED_ASSET.LAND",
      "collectionModesNotAllowed": [
        "DD"
      ],
      "partPaymentAllowed": false,
      "isAdvanceAllowed": false,
      "isVoucherCreationEnabled": true,
      "isActive": true,
      "type": "Finance"
    },
    {
      "businessService": "Disposal of Fixed Asset.Building",
      "code": "DISP_FIXED_ASSET.BUILDING",
      "collectionModesNotAllowed": [
        "DD"
      ],
      "partPaymentAllowed": false,
      "isAdvanceAllowed": false,
      "isVoucherCreationEnabled": true,
      "isActive": true,
      "type": "Finance"
    },
    {
      "businessService": "Disposal of Fixed Asset.Motor Vehicle",
      "code": "DISP_FIXED_ASSET.MOTOR_VEHICLE",
      "collectionModesNotAllowed": [
        "DD"
      ],
      "partPaymentAllowed": false,
      "isAdvanceAllowed": false,
      "isVoucherCreationEnabled": true,
      "isActive": true,
      "type": "Finance"
    },
    {
      "businessService": "BPARegistration",
      "code": "BPAREG",
      "collectionModesNotAllowed": [
        "DD"
      ],
      "partPaymentAllowed": false,
      "isAdvanceAllowed": false,
      "isVoucherCreationEnabled": true,
      "isActive": true
    },
    {
      "businessService": "ws-services-calculation",
      "code": "WS",
      "collectionModesNotAllowed": [
        "DD"
      ],
      "partPaymentAllowed": true,
      "isAdvanceAllowed": true,
      "demandUpdateTime": 86400000,
      "isVoucherCreationEnabled": false,
      "billGineiURL" : "egov-searcher/bill-genie/waterbills/_get"
    },
      {
      "businessService": "sw-services-calculation",
      "code": "SW",
      "collectionModesNotAllowed": [
        "DD","OFFLINE_NEFT","OFFLINE_RTGS","POSTAL_ORDER"
      ],
      "partPaymentAllowed": true,
      "isAdvanceAllowed": true,
      "demandUpdateTime": 86400000,
      "isVoucherCreationEnabled": false,
      "billGineiURL" : "egov-searcher/bill-genie/seweragebills/_get"
    },
    {
      "businessService": "BPA.NEWCONSTRUCTION_APP_FEE",
      "code": "BPA.NC_APP_FEE",
      "collectionModesNotAllowed": [
        "DD"
      ],
      "partPaymentAllowed": false,
      "isAdvanceAllowed": false,
      "isVoucherCreationEnabled": true,
      "isActive": true
    },
    {
      "businessService": "BPA.NEWCONSTRUCTION_SANC_FEE",
      "code": "BPA.NC_SAN_FEE",
      "collectionModesNotAllowed": [
        "DD"
      ],
      "partPaymentAllowed": false,
      "isAdvanceAllowed": false,
      "isVoucherCreationEnabled": true,
      "isActive": true
    },
    {
      "businessService": "BPA.NEWCONSTRUCTION_LOW_RISK_PERMIT_FEE",
      "code": "BPA.LOW_RISK_PERMIT_FEE",
      "collectionModesNotAllowed": [
        "DD"
      ],
      "partPaymentAllowed": false,
      "isAdvanceAllowed": false,
      "isVoucherCreationEnabled": true,
      "isActive": true
    },
    {
      "businessService": "PT.MUTATION",
      "code": "PT.MUTATION",
      "collectionModesNotAllowed": [
        "DD"
      ],
      "partPaymentAllowed": false,
      "isAdvanceAllowed": false,
      "isVoucherCreationEnabled": true,
      "isActive": true
    },
    {
      "businessService": "TL.RENEWAL",
      "code": "TL.RENEWAL",
      "collectionModesNotAllowed": [
        "DD"
      ],
      "partPaymentAllowed": false,
      "isAdvanceAllowed": false,
      "isVoucherCreationEnabled": true,
      "isActive": true
    },
    {
      "businessService": "WS.ONE_TIME_FEE",
      "code": "WS.ONE_TIME_FEE",
      "collectionModesNotAllowed": [
        "DD"
      ],
      "partPaymentAllowed": false,
      "isAdvanceAllowed": false,
      "isVoucherCreationEnabled": true,
      "isActive": true
    },
     {
      "businessService": "SW.ONE_TIME_FEE",
      "code": "SW.ONE_TIME_FEE",
      "collectionModesNotAllowed": [
        "DD"
      ],
      "partPaymentAllowed": false,
      "isAdvanceAllowed": false,
      "isVoucherCreationEnabled": true,
      "isActive": true
    },
     {
      "businessService": "BPA.NEWCONSTRUCTION_OC_APP_FEE",
      "code": "BPA.NC_OC_APP_FEE",
      "collectionModesNotAllowed": [
        "DD"
      ],
      "partPaymentAllowed": false,
      "isAdvanceAllowed": false,
      "isVoucherCreationEnabled": true,
      "isActive": true
    },
    {
      "businessService": "BPA.NEWCONSTRUCTION_OC_SANC_FEE",
      "code": "BPA.NC_OC_SAN_FEE",
      "collectionModesNotAllowed": [
        "DD"
      ],
      "partPaymentAllowed": false,
      "isAdvanceAllowed": false,
      "isVoucherCreationEnabled": true,
      "isActive": true
    }
  ]
}
