{
  "tenantId": "pb",
  "moduleName": "FinanceModule",
  "AccountCodeTemplate": [
    {
      "code": "EB1",
      "name": "Electricity Bill Template",
      "description": "Predefined set of account code for Electricity Bill",
      "module": "ExpenseBill",
      "subModule": "Contingent",
      "subledgerType": "Contractor",
      "debitCodeDetails": [
        {
          "glcode": 2300101
        }
      ],
      "creditCodeDetails": [
        {
          "glcode": 3501108
        },
        {
          "glcode": 3502023
        }
      ],
      "netPayable": {
        "glcode": 3501002
      }
    },
    {
      "code": "EB2",
      "name": "Electricity Bill Non Subledger Template",
      "description": "Predefined set of account code for Electricity Bill",
      "module": "ExpenseBill",
      "subModule": "Contingent",
      "subledgerType": null,
      "debitCodeDetails": [
        {
          "glcode": 2300101
        }
      ],
      "creditCodeDetails": [
        {
          "glcode": 3502023
        }
      ],
      "netPayable": {
        "glcode": 3501003
      }
    },
    {
      "code": "TB1",
      "name": "Travel Bill",
      "description": "Predefined set of account code for Travel Bill",
      "module": "ExpenseBill",
      "subModule": "Others",
      "subledgerType": null,
      "debitCodeDetails": [
        {
          "glcode": 2102016
        }
      ],
      "creditCodeDetails": [],
      "netPayable": {
        "glcode": 3501003
      }
    },
    {
      "code": "AE1",
      "name": "Administrative Expenses",
      "description": "Predefined set of account code for Administrative Expenses with subledger details",
      "module": "ExpenseBill",
      "subModule": "Others",
      "subledgerType": "Contractor",
      "debitCodeDetails": [
        {
          "glcode": 2201003
        },
        {
          "glcode": 2201002
        }
      ],
      "creditCodeDetails": [
        {
          "glcode": 3502001
        }
      ],
      "netPayable": {
        "glcode": 3501003
      }
    },
    {
      "code": "AE2",
      "name": "Administrative Expenses Non Subledger Template",
      "description": "Predefined set of account code for Administrative Expenses non subledger details",
      "module": "ExpenseBill",
      "subModule": "Others",
      "subledgerType": null,
      "debitCodeDetails": [
        {
          "glcode": 2208001
        },
        {
          "glcode": 2208011
        },
        {
          "glcode": 2208004
        }
      ],
      "creditCodeDetails": [
        {
          "glcode": 3501109
        },
        {
          "glcode": 3402003
        }
      ],
      "netPayable": {
        "glcode": 3501003
      }
    },
    {
      "code": "S&WB1",
      "name": "Salaries and Wages",
      "description": "Predefined set of account code for Salaries and Wages",
      "module": "ExpenseBill",
      "subModule": "Salary",
      "subledgerType": "DrawingOfficer",
      "debitCodeDetails": [
        {
          "glcode": 2101001
        },
        {
          "glcode": 2101002
        },
        {
          "glcode": 2101011
        }
      ],
      "creditCodeDetails": [
        {
          "glcode": 3502002
        },
        {
          "glcode": 3502008
        }
      ],
      "netPayable": {
        "glcode": 3501003
      }
    },
    {
      "code": "S&WB2",
      "name": "Salaries and Wages Non Subledger Template",
      "description": "Predefined set of account code for Salaries and Wage non subledger details",
      "module": "ExpenseBill",
      "subModule": "Salary",
      "subledgerType": null,
      "debitCodeDetails": [
        {
          "glcode": 2101001
        },
        {
          "glcode": 2102002
        },
        {
          "glcode": 2101011
        }
      ],
      "creditCodeDetails": [
        {
          "glcode": 3502023
        }
      ],
      "netPayable": {
        "glcode": 3501003
      }
    },
    {
      "code": "TELEBILL",
      "name": "Telephone Bills Non Subledger Template",
      "description": "Predefined set of account code for Telephone Expense Template non subledger details",
      "module": "ExpenseBill",
      "subModule": "Others",
      "subledgerType": null,
      "debitCodeDetails": [
        {
          "glcode": 2105003
        },
        {
          "glcode": 2201206
        },
        {
          "glcode": 2305320
        }
      ],
      "creditCodeDetails": [],
      "netPayable": {
        "glcode": 3501003
      }
    },
    {
      "code": "SDB",
      "name": "Security Deposit",
      "description": "Predefined set of account code for Security Deposit Template",
      "module": "ExpenseBill",
      "subModule": "Deposit",
      "subledgerType": "Contractor",
      "debitCodeDetails": [
        {
          "glcode": 2304003
        }
      ],
      "creditCodeDetails": [
        {
          "glcode": 3401002
        }
      ],
      "netPayable": {
        "glcode": 3501002
      }
    },
    {
      "code": "WCB",
      "name": "Water Charges",
      "description": "Predefined set of account code for Water Charges Template",
      "module": "ExpenseBill",
      "subModule": "Others",
      "subledgerType": null,
      "debitCodeDetails": [
        {
          "glcode": 2208014
        },
        {
          "glcode": 2302001
        },
        {
          "glcode": 2303006
        },
        {
          "glcode": 2305001
        }
      ],
      "creditCodeDetails": [
        {
          "glcode": 3503006
        }
      ],
      "netPayable": {
        "glcode": 3501003
      }
    },
    {
      "code": "PB",
      "name": "Pension",
      "description": "Predefined set of account code for Pension Template",
      "module": "ExpenseBill",
      "subModule": "Pension",
      "subledgerType": null,
      "debitCodeDetails": [
        {
          "glcode": 2103001
        },
        {
          "glcode": 2103002
        },
        {
          "glcode": 2103003
        },
        {
          "glcode": 2103004
        }
      ],
      "creditCodeDetails": [],
      "netPayable": {
        "glcode": 3501003
      }
    }
  ]
}
