{
  "tenantId": "default",
  "moduleName": "egf-bill",
  "BillStatus": [
    {
      "id": "1",
      "tenantId": "default",
      "name": "Created",
      "code": "Created",
      "moduleType": "Bill",
      "description": "Bill Created",
      "orderNumber": 1
    },
    {
      "id": "2",
      "tenantId": "default",
      "name": "Approved",
      "code": "Approved",
      "moduleType": "Bill",
      "description": "Bill Approved",
      "orderNumber": 2
    },
    {
      "id": "3",
      "tenantId": "default",
      "name": "Cancelled",
      "code": "Cancelled",
      "moduleType": "Bill",
      "description": "Bill Cancelled",
      "orderNumber": 3
    }
  ]
}
